README.rst
setup.py
zynlp/__init__.py
zynlp/zytext.py
zynlp.egg-info/PKG-INFO
zynlp.egg-info/SOURCES.txt
zynlp.egg-info/dependency_links.txt
zynlp.egg-info/top_level.txt